torch_geometric_median-0.1.1.dist-info/METADATA
torch_geometric_median-0.1.1.dist-info/WHEEL
torch_geometric_median-0.1.1.dist-info/licenses/LICENSE
torch_geometric_median/__init__.py
torch_geometric_median/geometric_median.py
torch_geometric_median/py.typed
torch_geometric_median-0.1.1.dist-info/RECORD
