Metadata-Version: 2.1
Name: torch-geometric-median
Version: 0.1.1
Summary: pytorch-optimized geometric median implementation
Author-Email: David Chanin <chanindav@gmail.com>
License: GPL
Requires-Python: >=3.10
Requires-Dist: torch>=2.0.0
Requires-Dist: tqdm>=4.0.0
